Metadata-Version: 2.1
Name: ml-distrib
Version: 1.0
Summary: Gaussian and Probability distributions for statistics and machine learning projects
Author: Joshua Shabo
Author-email: ma7zrono@gmail.com
